[{"item":"http://www.wikidata.org/entity/Q76473","itemLabel":"University of Southampton","ukprn":"10007158","grid":"grid.5491.9"},{"item":"http://www.wikidata.org/entity/Q932411","itemLabel":"Brunel University","ukprn":"10000961","grid":"grid.7728.a"},{"item":"http://www.wikidata.org/entity/Q4875952","itemLabel":"Beacon Hill Academy","ukprn":"10038611","grid":"grid.489428.b"},{"item":"http://www.wikidata.org/entity/Q16984484","itemLabel":"Blackpool and The Fylde College","ukprn":"10000754","grid":"grid.462095.c"},{"item":"http://www.wikidata.org/entity/Q170027","itemLabel":"University of London","ukprn":"10007797","grid":"grid.4464.2"},{"item":"http://www.wikidata.org/entity/Q174570","itemLabel":"London School of Economics and Political Science","ukprn":"10004063","grid":"grid.13063.37"},{"item":"http://www.wikidata.org/entity/Q262854","itemLabel":"University of Lancaster","ukprn":"10007768","grid":"grid.9835.7"},{"item":"http://www.wikidata.org/entity/Q270532","itemLabel":"University of Aberdeen","ukprn":"10007783","grid":"grid.7107.1"},{"item":"http://www.wikidata.org/entity/Q319761","itemLabel":"Aberystwyth University","ukprn":"10007856","grid":"grid.8186.7"},{"item":"http://www.wikidata.org/entity/Q459506","itemLabel":"University of Bristol","ukprn":"10007786","grid":"grid.5337.2"},{"item":"http://www.wikidata.org/entity/Q472316","itemLabel":"University of Nottingham","ukprn":"10007154","grid":"grid.4563.4"},{"item":"http://www.wikidata.org/entity/Q4892248","itemLabel":"Berkshire College of Agriculture","ukprn":"10000654","grid":"grid.468767.c"},{"item":"http://www.wikidata.org/entity/Q1737734","itemLabel":"University of Keele","ukprn":"10007767","grid":"grid.9757.c"},{"item":"http://www.wikidata.org/entity/Q1760791","itemLabel":"Middlesex University","ukprn":"10004351","grid":"grid.15822.3c"},{"item":"http://www.wikidata.org/entity/Q1859178","itemLabel":"University of Strathclyde","ukprn":"10007805","grid":"grid.11984.35"},{"item":"http://www.wikidata.org/entity/Q1888771","itemLabel":"Manchester Metropolitan University","ukprn":"10004180","grid":"grid.25627.34"},{"item":"http://www.wikidata.org/entity/Q7417039","itemLabel":"Sandwell College","ukprn":"10005669","grid":"grid.502892.4"},{"item":"http://www.wikidata.org/entity/Q981195","itemLabel":"Central School of Speech and Drama","ukprn":"10007816","grid":"grid.417786.b"},{"item":"http://www.wikidata.org/entity/Q1094046","itemLabel":"City, University of London","ukprn":"10001478","grid":"grid.28577.3f"},{"item":"http://www.wikidata.org/entity/Q1138080","itemLabel":"Coventry University","ukprn":"10001726","grid":"grid.8096.7"},{"item":"http://www.wikidata.org/entity/Q1277357","itemLabel":"Edinburgh Napier University","ukprn":"10007772","grid":"grid.20409.3f"},{"item":"http://www.wikidata.org/entity/Q1345942","itemLabel":"University of East London","ukprn":"10007144","grid":"grid.60969.30"},{"item":"http://www.wikidata.org/entity/Q1422458","itemLabel":"University of Bath","ukprn":"10007850","grid":"grid.7340.0"},{"item":"http://www.wikidata.org/entity/Q1434547","itemLabel":"Loughborough University","ukprn":"10004113","grid":"grid.6571.5"},{"item":"http://www.wikidata.org/entity/Q3695681","itemLabel":"Norwich University of the Arts","ukprn":"10004775","grid":"grid.261220.5"},{"item":"http://www.wikidata.org/entity/Q4973675","itemLabel":"London South East Colleges","ukprn":"10000948","grid":"grid.468697.2"},{"item":"http://www.wikidata.org/entity/Q5327862","itemLabel":"Windsor Forest Colleges Group","ukprn":"10002107","grid":"grid.468825.5"},{"item":"http://www.wikidata.org/entity/Q7115461","itemLabel":"Oxford Spires Academy","ukprn":"10032598","grid":"grid.499457.2"},{"item":"http://www.wikidata.org/entity/Q540751","itemLabel":"Anglia Ruskin University","ukprn":"10000291","grid":"grid.5115.0"},{"item":"http://www.wikidata.org/entity/Q2065695","itemLabel":"Solent University","ukprn":"10006022","grid":"grid.31044.32"},{"item":"http://www.wikidata.org/entity/Q4972779","itemLabel":"Brockenhurst College","ukprn":"10000944","grid":"grid.253330.4"},{"item":"http://www.wikidata.org/entity/Q7971224","itemLabel":"Warwickshire College","ukprn":"10007859","grid":"grid.463009.8"},{"item":"http://www.wikidata.org/entity/Q546976","itemLabel":"University of Surrey","ukprn":"10007160","grid":"grid.5475.3"},{"item":"http://www.wikidata.org/entity/Q954035","itemLabel":"University of Bradford","ukprn":"10007785","grid":"grid.6268.a"},{"item":"http://www.wikidata.org/entity/Q4782977","itemLabel":"Aquinas College","ukprn":"10000330","grid":"grid.468789.c"},{"item":"http://www.wikidata.org/entity/Q4950301","itemLabel":"Bournemouth and Poole College","ukprn":"10000820","grid":"grid.462107.6"},{"item":"http://www.wikidata.org/entity/Q3551774","itemLabel":"University of Wales Trinity Saint David","ukprn":"10007858","grid":"grid.12362.34"},{"item":"http://www.wikidata.org/entity/Q5019038","itemLabel":"Calderdale College","ukprn":"10001093","grid":"grid.462141.4"},{"item":"http://www.wikidata.org/entity/Q15199219","itemLabel":"The Oakwood Academy","ukprn":"10047489","grid":"grid.450179.e"},{"item":"http://www.wikidata.org/entity/Q34433","itemLabel":"University of Oxford","ukprn":"10007774","grid":"grid.4991.5"},{"item":"http://www.wikidata.org/entity/Q286216","itemLabel":"Leeds College of Music","ukprn":"10034449","grid":"grid.450940.c"},{"item":"http://www.wikidata.org/entity/Q823917","itemLabel":"University of Sheffield","ukprn":"10007157","grid":"grid.11835.3e"},{"item":"http://www.wikidata.org/entity/Q837164","itemLabel":"Newcastle University","ukprn":"10007799","grid":"grid.1006.7"},{"item":"http://www.wikidata.org/entity/Q963530","itemLabel":"University of Stirling","ukprn":"10007804","grid":"grid.11918.30"},{"item":"http://www.wikidata.org/entity/Q3182956","itemLabel":"Canterbury Christ Church University","ukprn":"10001143","grid":"grid.127050.1"},{"item":"http://www.wikidata.org/entity/Q3446028","itemLabel":"Royal Conservatoire of Scotland","ukprn":"10005561","grid":"grid.451002.2"},{"item":"http://www.wikidata.org/entity/Q3551402","itemLabel":"De Montfort University","ukprn":"10001883","grid":"grid.48815.30"},{"item":"http://www.wikidata.org/entity/Q5189653","itemLabel":"Croydon College","ukprn":"10001778","grid":"grid.462059.c"},{"item":"http://www.wikidata.org/entity/Q6686153","itemLabel":"Loughborough College","ukprn":"10004112","grid":"grid.462517.3"},{"item":"http://www.wikidata.org/entity/Q6919048","itemLabel":"Moulton College","ukprn":"10004442","grid":"grid.462560.3"},{"item":"http://www.wikidata.org/entity/Q7017390","itemLabel":"Newcastle College","ukprn":"10004599","grid":"grid.436306.4"},{"item":"http://www.wikidata.org/entity/Q181177","itemLabel":"Cranfield University","ukprn":"10007822","grid":"grid.12026.37"},{"item":"http://www.wikidata.org/entity/Q289348","itemLabel":"London South Bank University","ukprn":"10004078","grid":"grid.4756.0"},{"item":"http://www.wikidata.org/entity/Q1161297","itemLabel":"University of Sussex","ukprn":"10007806","grid":"grid.12082.39"},{"item":"http://www.wikidata.org/entity/Q1752117","itemLabel":"Sheffield Hallam University","ukprn":"10005790","grid":"grid.5884.1"},{"item":"http://www.wikidata.org/entity/Q1849271","itemLabel":"Leeds Trinity University","ukprn":"10003863","grid":"grid.417900.b"},{"item":"http://www.wikidata.org/entity/Q3166571","itemLabel":"Lancaster Royal Grammar School","ukprn":"10033644","grid":"grid.484421.f"},{"item":"http://www.wikidata.org/entity/Q6415753","itemLabel":"Kirklees College","ukprn":"10003189","grid":"grid.462476.5"},{"item":"http://www.wikidata.org/entity/Q7447554","itemLabel":"Selby College","ukprn":"10005741","grid":"grid.462849.5"},{"item":"http://www.wikidata.org/entity/Q7936182","itemLabel":"Vision West Nottinghamshire College","ukprn":"10007427","grid":"grid.469276.8"},{"item":"http://www.wikidata.org/entity/Q15262551","itemLabel":"Northampton College","ukprn":"10007011","grid":"grid.469055.b"},{"item":"http://www.wikidata.org/entity/Q877925","itemLabel":"Queen's University Belfast","ukprn":"10005343","grid":"grid.4777.3"},{"item":"http://www.wikidata.org/entity/Q1249005","itemLabel":"University of Dundee","ukprn":"10007852","grid":"grid.8241.f"},{"item":"http://www.wikidata.org/entity/Q1432632","itemLabel":"University of Reading","ukprn":"10007802","grid":"grid.9435.b"},{"item":"http://www.wikidata.org/entity/Q1816872","itemLabel":"University of Gloucestershire","ukprn":"10007145","grid":"grid.21027.36"},{"item":"http://www.wikidata.org/entity/Q3442365","itemLabel":"Rose Bruford College","ukprn":"10005523","grid":"grid.450990.1"},{"item":"http://www.wikidata.org/entity/Q7375001","itemLabel":"Royal Welsh College of Music & Drama","ukprn":"10007838","grid":"grid.450991.0"},{"item":"http://www.wikidata.org/entity/Q7649440","itemLabel":"Sussex Downs College","ukprn":"10006432","grid":"grid.462872.d"},{"item":"http://www.wikidata.org/entity/Q7658423","itemLabel":"Swindon College","ukprn":"10006463","grid":"grid.462879.6"},{"item":"http://www.wikidata.org/entity/Q7989175","itemLabel":"Westminster Kingsway College","ukprn":"10007455","grid":"grid.463058.c"},{"item":"http://www.wikidata.org/entity/Q1857773","itemLabel":"University of Central Lancashire","ukprn":"10007141","grid":"grid.7943.9"},{"item":"http://www.wikidata.org/entity/Q5093795","itemLabel":"Chesterfield College","ukprn":"10001378","grid":"grid.468670.b"},{"item":"http://www.wikidata.org/entity/Q7527717","itemLabel":"Sir John Deane's College","ukprn":"10067306","grid":"grid.469201.8"},{"item":"http://www.wikidata.org/entity/Q7401329","itemLabel":"Saint Gregory's Catholic College","ukprn":"10017344","grid":"grid.438148.2"},{"item":"http://www.wikidata.org/entity/Q1668871","itemLabel":"Liverpool Institute for Performing Arts","ukprn":"10003945","grid":"grid.451001.1"},{"item":"http://www.wikidata.org/entity/Q4861050","itemLabel":"Barking and Dagenham College","ukprn":"10000528","grid":"grid.462069.f"},{"item":"http://www.wikidata.org/entity/Q195668","itemLabel":"Queen Mary University of London","ukprn":"10007775","grid":"grid.4868.2"},{"item":"http://www.wikidata.org/entity/Q3056815","itemLabel":"University of Huddersfield","ukprn":"10007148","grid":"grid.15751.37"},{"item":"http://www.wikidata.org/entity/Q3551690","itemLabel":"University of Winchester","ukprn":"10003614","grid":"grid.267454.6"},{"item":"http://www.wikidata.org/entity/Q4907619","itemLabel":"Bilborough College","ukprn":"10000695","grid":"grid.468792.6"},{"item":"http://www.wikidata.org/entity/Q4999956","itemLabel":"Burnley College","ukprn":"10001000","grid":"grid.462134.6"},{"item":"http://www.wikidata.org/entity/Q6840881","itemLabel":"MidKent College","ukprn":"10004340","grid":"grid.462575.7"},{"item":"http://www.wikidata.org/entity/Q7714615","itemLabel":"Arts University Bournemouth","ukprn":"10000385","grid":"grid.417908.3"},{"item":"http://www.wikidata.org/entity/Q3091754","itemLabel":"Bath Spa University","ukprn":"10000571","grid":"grid.252874.e"},{"item":"http://www.wikidata.org/entity/Q3551577","itemLabel":"University of Chichester","ukprn":"10007137","grid":"grid.266161.4"},{"item":"http://www.wikidata.org/entity/Q3835531","itemLabel":"Liverpool School of Tropical Medicine","ukprn":"10003958","grid":"grid.48004.38"},{"item":"http://www.wikidata.org/entity/Q4667848","itemLabel":"Abingdon and Witney College","ukprn":"10000055","grid":"grid.468658.1"},{"item":"http://www.wikidata.org/entity/Q7750158","itemLabel":"The Manchester College","ukprn":"10023139","grid":"grid.421110.7"},{"item":"http://www.wikidata.org/entity/Q4917489","itemLabel":"Bishop Auckland College","ukprn":"10000720","grid":"grid.468797.3"},{"item":"http://www.wikidata.org/entity/Q4940229","itemLabel":"Bolton Sixth Form College","ukprn":"10000796","grid":"grid.468655.c"},{"item":"http://www.wikidata.org/entity/Q5038449","itemLabel":"Cardiff Metropolitan University","ukprn":"10007854","grid":"grid.47170.35"},{"item":"http://www.wikidata.org/entity/Q5123283","itemLabel":"City Literary Institute","ukprn":"10001463","grid":"grid.461975.8"},{"item":"http://www.wikidata.org/entity/Q5123579","itemLabel":"City of Bath College","ukprn":"10001465","grid":"grid.468747.e"},{"item":"http://www.wikidata.org/entity/Q7739369","itemLabel":"The Henley College","ukprn":"10003011","grid":"grid.468844.2"},{"item":"http://www.wikidata.org/entity/Q5596621","itemLabel":"Grantham College","ukprn":"10002743","grid":"grid.468903.0"},{"item":"http://www.wikidata.org/entity/Q1610024","itemLabel":"Heriot-Watt University","ukprn":"10007764","grid":"grid.9531.e"},{"item":"http://www.wikidata.org/entity/Q1627967","itemLabel":"Liverpool John Moores University","ukprn":"10003957","grid":"grid.4425.7"},{"item":"http://www.wikidata.org/entity/Q2503794","itemLabel":"Northumbria University","ukprn":"10001282","grid":"grid.42629.3b"},{"item":"http://www.wikidata.org/entity/Q6515942","itemLabel":"Leeds College of Building","ukprn":"10003855","grid":"grid.503019.e"},{"item":"http://www.wikidata.org/entity/Q6658364","itemLabel":"The City of Liverpool College","ukprn":"10003955","grid":"grid.461980.2"},{"item":"http://www.wikidata.org/entity/Q7006607","itemLabel":"New College, Swindon","ukprn":"10004579","grid":"grid.469126.e"},{"item":"http://www.wikidata.org/entity/Q1818020","itemLabel":"Liverpool Hope University","ukprn":"10003956","grid":"grid.146189.3"},{"item":"http://www.wikidata.org/entity/Q2744209","itemLabel":"University of Portsmouth","ukprn":"10007155","grid":"grid.4701.2"},{"item":"http://www.wikidata.org/entity/Q4974673","itemLabel":"Brooklands College","ukprn":"10000950","grid":"grid.462125.6"},{"item":"http://www.wikidata.org/entity/Q7017320","itemLabel":"Newcastle-under-Lyme College","ukprn":"10004603","grid":"grid.462617.0"},{"item":"http://www.wikidata.org/entity/Q7074079","itemLabel":"Oaklands College","ukprn":"10004835","grid":"grid.462740.3"},{"item":"http://www.wikidata.org/entity/Q7103408","itemLabel":"Ormiston Bushfield Academy","ukprn":"10028072","grid":"grid.500686.d"},{"item":"http://www.wikidata.org/entity/Q7301469","itemLabel":"Reaseheath College","ukprn":"10005404","grid":"grid.469044.b"},{"item":"http://www.wikidata.org/entity/Q1516684","itemLabel":"University of Kent","ukprn":"10007150","grid":"grid.9759.2"},{"item":"http://www.wikidata.org/entity/Q2738646","itemLabel":"University of Lincoln","ukprn":"10007151","grid":"grid.36511.30"},{"item":"http://www.wikidata.org/entity/Q3123462","itemLabel":"University of Northampton","ukprn":"10007138","grid":"grid.44870.3f"},{"item":"http://www.wikidata.org/entity/Q5609317","itemLabel":"Grimsby Institute of Further and Higher Education","ukprn":"10007938","grid":"grid.482815.2"},{"item":"http://www.wikidata.org/entity/Q8055565","itemLabel":"York St John University","ukprn":"10007713","grid":"grid.23695.3b"},{"item":"http://www.wikidata.org/entity/Q15262510","itemLabel":"North East Surrey College of Technology","ukprn":"10004686","grid":"grid.462675.4"},{"item":"http://www.wikidata.org/entity/Q2392351","itemLabel":"Leeds Beckett University","ukprn":"10003861","grid":"grid.10346.30"},{"item":"http://www.wikidata.org/entity/Q5123606","itemLabel":"City of Bristol College","ukprn":"10001467","grid":"grid.461977.a"},{"item":"http://www.wikidata.org/entity/Q7986605","itemLabel":"West Suffolk College","ukprn":"10007431","grid":"grid.463035.7"},{"item":"http://www.wikidata.org/entity/Q8055404","itemLabel":"York College","ukprn":"10007709","grid":"grid.469314.d"},{"item":"http://www.wikidata.org/entity/Q1414861","itemLabel":"University of Exeter","ukprn":"10007792","grid":"grid.8391.3"},{"item":"http://www.wikidata.org/entity/Q7712185","itemLabel":"The Academy at Shotton Hall","ukprn":"10032958","grid":"grid.500990.5"},{"item":"http://www.wikidata.org/entity/Q5674793","itemLabel":"Hartlepool College of Further Education","ukprn":"10002917","grid":"grid.468961.4"},{"item":"http://www.wikidata.org/entity/Q6722921","itemLabel":"Macclesfield College","ukprn":"10004144","grid":"grid.468972.6"},{"item":"http://www.wikidata.org/entity/Q3047150","itemLabel":"University of Bedfordshire","ukprn":"10007152","grid":"grid.15034.33"},{"item":"http://www.wikidata.org/entity/Q17017438","itemLabel":"Nottingham University Samworth Academy","ukprn":"10025622","grid":"grid.500673.7"},{"item":"http://www.wikidata.org/entity/Q5663364","itemLabel":"Harper Adams University","ukprn":"10040812","grid":"grid.417899.a"},{"item":"http://www.wikidata.org/entity/Q16891977","itemLabel":"Wigston College","ukprn":"10039351","grid":"grid.502802.d"},{"item":"http://www.wikidata.org/entity/Q4865666","itemLabel":"Barton Peveril Sixth Form College","ukprn":"10000552","grid":"grid.468740.9"},{"item":"http://www.wikidata.org/entity/Q67149348","itemLabel":"Wiltshire College","ukprn":"10007527","grid":"grid.469305.d"},{"item":"http://www.wikidata.org/entity/Q193196","itemLabel":"University College London","ukprn":"10007766","grid":"grid.83440.3b"},{"item":"http://www.wikidata.org/entity/Q528231","itemLabel":"Goldsmiths, University of London","ukprn":"10002718","grid":"grid.15874.3f"},{"item":"http://www.wikidata.org/entity/Q1753535","itemLabel":"Royal College of Art","ukprn":"10007777","grid":"grid.42167.36"},{"item":"http://www.wikidata.org/entity/Q5108993","itemLabel":"Christ The King Sixth Form College","ukprn":"10001416","grid":"grid.468690.5"},{"item":"http://www.wikidata.org/entity/Q5247011","itemLabel":"Dearne Valley College","ukprn":"10001897","grid":"grid.502766.0"},{"item":"http://www.wikidata.org/entity/Q5432602","itemLabel":"Falmouth University","ukprn":"10008640","grid":"grid.43086.39"},{"item":"http://www.wikidata.org/entity/Q7178025","itemLabel":"Peterborough Regional College","ukprn":"10005077","grid":"grid.461298.0"},{"item":"http://www.wikidata.org/entity/Q8038568","itemLabel":"Writtle College","ukprn":"10007657","grid":"grid.451003.3"},{"item":"http://www.wikidata.org/entity/Q220144","itemLabel":"School of Oriental and African Studies, University of London","ukprn":"10007780","grid":"grid.22631.34"},{"item":"http://www.wikidata.org/entity/Q223429","itemLabel":"University of Birmingham","ukprn":"10006840","grid":"grid.6572.6"},{"item":"http://www.wikidata.org/entity/Q790029","itemLabel":"Bangor University","ukprn":"10007857","grid":"grid.7362.0"},{"item":"http://www.wikidata.org/entity/Q865528","itemLabel":"University of Warwick","ukprn":"10007163","grid":"grid.7372.1"},{"item":"http://www.wikidata.org/entity/Q1481050","itemLabel":"London Business School","ukprn":"10007769","grid":"grid.14868.33"},{"item":"http://www.wikidata.org/entity/Q1896148","itemLabel":"University of Greenwich","ukprn":"10007146","grid":"grid.36316.31"},{"item":"http://www.wikidata.org/entity/Q2738622","itemLabel":"University of Salford","ukprn":"10007156","grid":"grid.8752.8"},{"item":"http://www.wikidata.org/entity/Q3228965","itemLabel":"Leeds Arts University","ukprn":"10003854","grid":"grid.451094.d"},{"item":"http://www.wikidata.org/entity/Q3400501","itemLabel":"Wrexham Glyndŵr University","ukprn":"10007833","grid":"grid.4862.8"},{"item":"http://www.wikidata.org/entity/Q5123991","itemLabel":"City of Wolverhampton College","ukprn":"10007578","grid":"grid.461982.0"},{"item":"http://www.wikidata.org/entity/Q5142110","itemLabel":"Colchester Sixth Form College","ukprn":"10005881","grid":"grid.502935.8"},{"item":"http://www.wikidata.org/entity/Q6413557","itemLabel":"Kingston Maurward College","ukprn":"10003676","grid":"grid.468929.8"},{"item":"http://www.wikidata.org/entity/Q6947437","itemLabel":"Myerscough College","ukprn":"10004478","grid":"grid.462615.2"},{"item":"http://www.wikidata.org/entity/Q7241864","itemLabel":"Preston College","ukprn":"10005200","grid":"grid.469121.9"},{"item":"http://www.wikidata.org/entity/Q7296496","itemLabel":"Ravensbourne","ukprn":"10005389","grid":"grid.450941.d"},{"item":"http://www.wikidata.org/entity/Q7573803","itemLabel":"Sparsholt College","ukprn":"10006050","grid":"grid.469219.1"},{"item":"http://www.wikidata.org/entity/Q7961036","itemLabel":"Wakefield College","ukprn":"10007289","grid":"grid.462990.0"},{"item":"http://www.wikidata.org/entity/Q15262543","itemLabel":"North Warwickshire and South Leicestershire College","ukprn":"10004718","grid":"grid.469053.d"},{"item":"http://www.wikidata.org/entity/Q8043180","itemLabel":"Xaverian College","ukprn":"10007682","grid":"grid.469324.e"},{"item":"http://www.wikidata.org/entity/Q35794","itemLabel":"University of Cambridge","ukprn":"10007788","grid":"grid.5335.0"},{"item":"http://www.wikidata.org/entity/Q189022","itemLabel":"Imperial College London","ukprn":"10003270","grid":"grid.7445.2"},{"item":"http://www.wikidata.org/entity/Q192775","itemLabel":"University of Glasgow","ukprn":"10007794","grid":"grid.8756.c"},{"item":"http://www.wikidata.org/entity/Q268411","itemLabel":"Royal Veterinary College","ukprn":"10007779","grid":"grid.20931.39"},{"item":"http://www.wikidata.org/entity/Q4916750","itemLabel":"Birmingham Metropolitan College","ukprn":"10006442","grid":"grid.462086.e"},{"item":"http://www.wikidata.org/entity/Q503424","itemLabel":"University of Leeds","ukprn":"10007795","grid":"grid.9909.9"},{"item":"http://www.wikidata.org/entity/Q762243","itemLabel":"University of Chester","ukprn":"10007848","grid":"grid.43710.31"},{"item":"http://www.wikidata.org/entity/Q772421","itemLabel":"St George's, University of London","ukprn":"10007782","grid":"grid.264200.2"},{"item":"http://www.wikidata.org/entity/Q1045828","itemLabel":"University of East Anglia","ukprn":"10007789","grid":"grid.8273.e"},{"item":"http://www.wikidata.org/entity/Q4807195","itemLabel":"Askham Bryan College","ukprn":"10000415","grid":"grid.459384.7"},{"item":"http://www.wikidata.org/entity/Q4922668","itemLabel":"Blackburn College","ukprn":"10000747","grid":"grid.462090.9"},{"item":"http://www.wikidata.org/entity/Q5121865","itemLabel":"Cirencester College","ukprn":"10001446","grid":"grid.468702.f"},{"item":"http://www.wikidata.org/entity/Q5757880","itemLabel":"Highbury College","ukprn":"10007945","grid":"grid.462262.6"},{"item":"http://www.wikidata.org/entity/Q1420500","itemLabel":"Swansea University","ukprn":"10007855","grid":"grid.4827.9"},{"item":"http://www.wikidata.org/entity/Q1534573","itemLabel":"Staffordshire University","ukprn":"10006299","grid":"grid.19873.34"},{"item":"http://www.wikidata.org/entity/Q1683230","itemLabel":"University of Bolton","ukprn":"10006841","grid":"grid.36076.34"},{"item":"http://www.wikidata.org/entity/Q1710482","itemLabel":"London School of Theology","ukprn":"10004075","grid":"grid.462506.3"},{"item":"http://www.wikidata.org/entity/Q1711558","itemLabel":"University of Plymouth","ukprn":"10007801","grid":"grid.11201.33"},{"item":"http://www.wikidata.org/entity/Q2007778","itemLabel":"University of West London","ukprn":"10006566","grid":"grid.81800.31"},{"item":"http://www.wikidata.org/entity/Q2503809","itemLabel":"Kingston University","ukprn":"10003678","grid":"grid.15538.3a"},{"item":"http://www.wikidata.org/entity/Q7598848","itemLabel":"Stanground Academy","ukprn":"10036496","grid":"grid.470108.a"},{"item":"http://www.wikidata.org/entity/Q3036648","itemLabel":"University of Worcester","ukprn":"10007139","grid":"grid.189530.6"},{"item":"http://www.wikidata.org/entity/Q3056813","itemLabel":"University of Brighton","ukprn":"10000886","grid":"grid.12477.37"},{"item":"http://www.wikidata.org/entity/Q3182943","itemLabel":"Bournemouth University","ukprn":"10000824","grid":"grid.17236.31"},{"item":"http://www.wikidata.org/entity/Q641609","itemLabel":"Heythrop College, University of London","ukprn":"10007765","grid":"grid.450939.2"},{"item":"http://www.wikidata.org/entity/Q3531508","itemLabel":"Tonbridge School","ukprn":"10006936","grid":"grid.482792.2"},{"item":"http://www.wikidata.org/entity/Q4917580","itemLabel":"Bishop Grosseteste University","ukprn":"10007811","grid":"grid.417784.9"},{"item":"http://www.wikidata.org/entity/Q4966922","itemLabel":"Bridgwater and Taunton College","ukprn":"10000878","grid":"grid.462117.7"},{"item":"http://www.wikidata.org/entity/Q5001080","itemLabel":"Bury College","ukprn":"10001005","grid":"grid.462136.4"},{"item":"http://www.wikidata.org/entity/Q5675151","itemLabel":"Hartpury College","ukprn":"10080810","grid":"grid.507380.9"},{"item":"http://www.wikidata.org/entity/Q6039999","itemLabel":"Institute of Cancer Research","ukprn":"10003324","grid":"grid.18886.3f"},{"item":"http://www.wikidata.org/entity/Q5060602","itemLabel":"Central College Nottingham","ukprn":"10005991","grid":"grid.462177.1"},{"item":"http://www.wikidata.org/entity/Q5527146","itemLabel":"Gateshead College","ukprn":"10002638","grid":"grid.462249.f"},{"item":"http://www.wikidata.org/entity/Q5641515","itemLabel":"Halesowen College","ukprn":"10002852","grid":"grid.462290.b"},{"item":"http://www.wikidata.org/entity/Q1474019","itemLabel":"University of Hull","ukprn":"10007149","grid":"grid.9481.4"},{"item":"http://www.wikidata.org/entity/Q4879121","itemLabel":"Bedford College","ukprn":"10000610","grid":"grid.461925.d"},{"item":"http://www.wikidata.org/entity/Q5885193","itemLabel":"Holy Cross College","ukprn":"10003128","grid":"grid.468885.f"},{"item":"http://www.wikidata.org/entity/Q7558060","itemLabel":"Solihull College","ukprn":"10005946","grid":"grid.469222.9"},{"item":"http://www.wikidata.org/entity/Q7568534","itemLabel":"South Staffordshire College","ukprn":"10023526","grid":"grid.462880.0"},{"item":"http://www.wikidata.org/entity/Q7624231","itemLabel":"Strode College","ukprn":"10006378","grid":"grid.469194.7"},{"item":"http://www.wikidata.org/entity/Q7859526","itemLabel":"Twyford Church of England High School","ukprn":"10035500","grid":"grid.438880.f"},{"item":"http://www.wikidata.org/entity/Q1505925","itemLabel":"University of Abertay Dundee","ukprn":"10007849","grid":"grid.44361.34"},{"item":"http://www.wikidata.org/entity/Q7621650","itemLabel":"Stranmillis University College","ukprn":"10008010","grid":"grid.470672.0"},{"item":"http://www.wikidata.org/entity/Q7894637","itemLabel":"University of St Mark & St John","ukprn":"10037449","grid":"grid.418024.b"},{"item":"http://www.wikidata.org/entity/Q8052493","itemLabel":"Yeovil College","ukprn":"10007696","grid":"grid.469304.c"},{"item":"http://www.wikidata.org/entity/Q1788342","itemLabel":"Robert Gordon University","ukprn":"10005500","grid":"grid.59490.31"},{"item":"http://www.wikidata.org/entity/Q15261973","itemLabel":"Nottingham College","ukprn":"10004577","grid":"grid.507468.8"},{"item":"http://www.wikidata.org/entity/Q750066","itemLabel":"Aston University","ukprn":"10007759","grid":"grid.7273.1"},{"item":"http://www.wikidata.org/entity/Q1745633","itemLabel":"University of Hertfordshire","ukprn":"10007147","grid":"grid.5846.f"},{"item":"http://www.wikidata.org/entity/Q5171960","itemLabel":"Cornwall College","ukprn":"10001696","grid":"grid.470922.a"},{"item":"http://www.wikidata.org/entity/Q7380113","itemLabel":"Runshaw College","ukprn":"10005575","grid":"grid.469118.3"},{"item":"http://www.wikidata.org/entity/Q7570957","itemLabel":"Southport College","ukprn":"10006038","grid":"grid.462918.0"},{"item":"http://www.wikidata.org/entity/Q5935849","itemLabel":"Hull College","ukprn":"10003200","grid":"grid.462279.c"},{"item":"http://www.wikidata.org/entity/Q24661246","itemLabel":"University of Suffolk","ukprn":"10014001","grid":"grid.449668.1"},{"item":"http://www.wikidata.org/entity/Q448807","itemLabel":"National Film and Television School","ukprn":"10004511","grid":"grid.451095.c"},{"item":"http://www.wikidata.org/entity/Q5223980","itemLabel":"Darlington College","ukprn":"10001850","grid":"grid.462083.b"},{"item":"http://www.wikidata.org/entity/Q5329257","itemLabel":"East Riding College","ukprn":"10002126","grid":"grid.468830.1"},{"item":"http://www.wikidata.org/entity/Q7308066","itemLabel":"Regent's University London","ukprn":"10003331","grid":"grid.449469.2"},{"item":"http://www.wikidata.org/entity/Q15261971","itemLabel":"New College Durham","ukprn":"10004576","grid":"grid.462655.6"},{"item":"http://www.wikidata.org/entity/Q939607","itemLabel":"Roehampton University","ukprn":"10007776","grid":"grid.35349.38"},{"item":"http://www.wikidata.org/entity/Q1126189","itemLabel":"London School of Hygiene & Tropical Medicine","ukprn":"10007771","grid":"grid.8991.9"},{"item":"http://www.wikidata.org/entity/Q1202039","itemLabel":"Royal Holloway, University of London","ukprn":"10005553","grid":"grid.4970.a"},{"item":"http://www.wikidata.org/entity/Q3445856","itemLabel":"Royal Agricultural University","ukprn":"10005545","grid":"grid.417905.e"},{"item":"http://www.wikidata.org/entity/Q3445966","itemLabel":"Royal Hospital School","ukprn":"10008469","grid":"grid.461321.3"},{"item":"http://www.wikidata.org/entity/Q3547145","itemLabel":"Birmingham City University","ukprn":"10007140","grid":"grid.19822.30"},{"item":"http://www.wikidata.org/entity/Q5434953","itemLabel":"Fareham College","ukprn":"10007928","grid":"grid.468836.7"},{"item":"http://www.wikidata.org/entity/Q6747415","itemLabel":"The Manchester Grammar School","ukprn":"10008373","grid":"grid.454326.2"},{"item":"http://www.wikidata.org/entity/Q7593338","itemLabel":"St Helens College","ukprn":"10006174","grid":"grid.462827.d"},{"item":"http://www.wikidata.org/entity/Q2065666","itemLabel":"University of the Arts London","ukprn":"10007162","grid":"grid.20364.33"},{"item":"http://www.wikidata.org/entity/Q8034708","itemLabel":"Workers' Educational Association","ukprn":"10007364","grid":"grid.439360.b"},{"item":"http://www.wikidata.org/entity/Q7330984","itemLabel":"Richmond School","ukprn":"10065396","grid":"grid.502896.0"},{"item":"http://www.wikidata.org/entity/Q216273","itemLabel":"University of St Andrews","ukprn":"10007803","grid":"grid.11914.3c"},{"item":"http://www.wikidata.org/entity/Q160302","itemLabel":"University of Edinburgh","ukprn":"10007790","grid":"grid.4305.2"},{"item":"http://www.wikidata.org/entity/Q304985","itemLabel":"Royal College of Music","ukprn":"10007778","grid":"grid.421665.2"},{"item":"http://www.wikidata.org/entity/Q375606","itemLabel":"Birkbeck, University of London","ukprn":"10007760","grid":"grid.88379.3d"},{"item":"http://www.wikidata.org/entity/Q1353139","itemLabel":"Glasgow Caledonian University","ukprn":"10007762","grid":"grid.5214.2"},{"item":"http://www.wikidata.org/entity/Q1627864","itemLabel":"Ruskin College","ukprn":"10005583","grid":"grid.469119.2"},{"item":"http://www.wikidata.org/entity/Q1869028","itemLabel":"London Metropolitan University","ukprn":"10004048","grid":"grid.23231.31"},{"item":"http://www.wikidata.org/entity/Q2096524","itemLabel":"Ulster University","ukprn":"10007807","grid":"grid.12641.30"},{"item":"http://www.wikidata.org/entity/Q4710828","itemLabel":"Newman University","ukprn":"10007832","grid":"grid.417901.a"},{"item":"http://www.wikidata.org/entity/Q5163126","itemLabel":"Conservatoire for Dance and Drama","ukprn":"10001653","grid":"grid.417787.a"},{"item":"http://www.wikidata.org/entity/Q5182719","itemLabel":"Craven College","ukprn":"10001743","grid":"grid.468719.5"},{"item":"http://www.wikidata.org/entity/Q5683811","itemLabel":"Havering College of Further and Higher Education","ukprn":"10002935","grid":"grid.502820.d"},{"item":"http://www.wikidata.org/entity/Q7205783","itemLabel":"Plymouth College of Art","ukprn":"10005127","grid":"grid.451096.f"},{"item":"http://www.wikidata.org/entity/Q7435613","itemLabel":"Scotland's Rural College","ukprn":"10005700","grid":"grid.426884.4"},{"item":"http://www.wikidata.org/entity/Q7567040","itemLabel":"South Devon College","ukprn":"10005977","grid":"grid.469242.f"},{"item":"http://www.wikidata.org/entity/Q7963763","itemLabel":"Walsall Academy","ukprn":"10015885","grid":"grid.482814.3"},{"item":"http://www.wikidata.org/entity/Q5123937","itemLabel":"City of Stoke-on-Trent Sixth Form College","ukprn":"10065146","grid":"grid.502928.4"},{"item":"http://www.wikidata.org/entity/Q132478","itemLabel":"Oxford Brookes University","ukprn":"10004930","grid":"grid.7628.b"},{"item":"http://www.wikidata.org/entity/Q192088","itemLabel":"Eton College","ukprn":"10008228","grid":"grid.482809.f"},{"item":"http://www.wikidata.org/entity/Q245247","itemLabel":"King's College London","ukprn":"10003645","grid":"grid.13097.3c"},{"item":"http://www.wikidata.org/entity/Q379124","itemLabel":"Trinity Laban Conservatoire of Music and Dance","ukprn":"10008017","grid":"grid.421855.f"},{"item":"http://www.wikidata.org/entity/Q915989","itemLabel":"Queen Margaret University","ukprn":"10005337","grid":"grid.104846.f"},{"item":"http://www.wikidata.org/entity/Q7894613","itemLabel":"University College Birmingham","ukprn":"10000712","grid":"grid.418023.c"},{"item":"http://www.wikidata.org/entity/Q1035745","itemLabel":"Cardiff University","ukprn":"10007814","grid":"grid.5600.3"},{"item":"http://www.wikidata.org/entity/Q1094742","itemLabel":"University of Sunderland","ukprn":"10007159","grid":"grid.7110.7"},{"item":"http://www.wikidata.org/entity/Q1419737","itemLabel":"Guildhall School of Music and Drama","ukprn":"10007825","grid":"grid.434939.0"},{"item":"http://www.wikidata.org/entity/Q1816202","itemLabel":"University of Wolverhampton","ukprn":"10007166","grid":"grid.6374.6"},{"item":"http://www.wikidata.org/entity/Q1861974","itemLabel":"University of Cumbria","ukprn":"10007842","grid":"grid.266218.9"},{"item":"http://www.wikidata.org/entity/Q2002619","itemLabel":"Nottingham Trent University","ukprn":"10004797","grid":"grid.12361.37"},{"item":"http://www.wikidata.org/entity/Q5123988","itemLabel":"United Colleges Group","ukprn":"10001476","grid":"grid.464536.6"},{"item":"http://www.wikidata.org/entity/Q2321391","itemLabel":"St Mary's University, Twickenham","ukprn":"10007843","grid":"grid.417907.c"},{"item":"http://www.wikidata.org/entity/Q2413375","itemLabel":"The Open University","ukprn":"10007773","grid":"grid.10837.3d"},{"item":"http://www.wikidata.org/entity/Q4954635","itemLabel":"Bradford College","ukprn":"10000840","grid":"grid.462112.2"},{"item":"http://www.wikidata.org/entity/Q6658359","itemLabel":"Liverpool College","ukprn":"10041615","grid":"grid.502844.f"},{"item":"http://www.wikidata.org/entity/Q3695910","itemLabel":"Teesside University","ukprn":"10007161","grid":"grid.26597.3f"},{"item":"http://www.wikidata.org/entity/Q4852575","itemLabel":"Balshaw's Church of England High School","ukprn":"10015034","grid":"grid.497941.6"},{"item":"http://www.wikidata.org/entity/Q5142094","itemLabel":"Colchester Institute","ukprn":"10001535","grid":"grid.462006.6"},{"item":"http://www.wikidata.org/entity/Q2598272","itemLabel":"University for the Creative Arts","ukprn":"10006427","grid":"grid.51008.3c"},{"item":"http://www.wikidata.org/entity/Q5929941","itemLabel":"Hugh Baird College","ukprn":"10003193","grid":"grid.468912.0"},{"item":"http://www.wikidata.org/entity/Q6515867","itemLabel":"Leeds City College","ukprn":"10024962","grid":"grid.437235.4"},{"item":"http://www.wikidata.org/entity/Q7270382","itemLabel":"The Queen Elizabeth Academy","ukprn":"10042700","grid":"grid.500799.2"},{"item":"http://www.wikidata.org/entity/Q7568689","itemLabel":"Tyne Coast College","ukprn":"10005999","grid":"grid.462885.5"},{"item":"http://www.wikidata.org/entity/Q7569110","itemLabel":"Southampton City College","ukprn":"10006020","grid":"grid.469167.b"},{"item":"http://www.wikidata.org/entity/Q4917504","itemLabel":"Bishop Burton College","ukprn":"10000721","grid":"grid.468799.d"},{"item":"http://www.wikidata.org/entity/Q4940147","itemLabel":"Bolton College","ukprn":"10000794","grid":"grid.468817.4"},{"item":"http://www.wikidata.org/entity/Q7567367","itemLabel":"South Gloucestershire and Stroud College","ukprn":"10036143","grid":"grid.469139.0"},{"item":"http://www.wikidata.org/entity/Q7963767","itemLabel":"Walsall College","ukprn":"10007315","grid":"grid.463002.3"},{"item":"http://www.wikidata.org/entity/Q7018113","itemLabel":"Newham College of Further Education","ukprn":"10004607","grid":"grid.462621.5"},{"item":"http://www.wikidata.org/entity/Q1544384","itemLabel":"Royal Northern College of Music","ukprn":"10007837","grid":"grid.437498.5"},{"item":"http://www.wikidata.org/entity/Q7634576","itemLabel":"Suffolk New College","ukprn":"10006398","grid":"grid.462891.0"},{"item":"http://www.wikidata.org/entity/Q193196","itemLabel":"University College London","ukprn":"10007781","grid":"grid.83440.3b"},{"item":"http://www.wikidata.org/entity/Q193196","itemLabel":"University College London","ukprn":"10007784","grid":"grid.83440.3b"},{"item":"http://www.wikidata.org/entity/Q230899","itemLabel":"University of Manchester","ukprn":"10007798","grid":"grid.5379.8"},{"item":"http://www.wikidata.org/entity/Q734266","itemLabel":"Courtauld Institute of Art","ukprn":"10007761","grid":"grid.424182.9"},{"item":"http://www.wikidata.org/entity/Q1247544","itemLabel":"University of Westminster","ukprn":"10007165","grid":"grid.12896.34"},{"item":"http://www.wikidata.org/entity/Q1971174","itemLabel":"University of South Wales","ukprn":"10007793","grid":"grid.410658.e"},{"item":"http://www.wikidata.org/entity/Q2002520","itemLabel":"University of the West of England, Bristol","ukprn":"10007164","grid":"grid.6518.a"},{"item":"http://www.wikidata.org/entity/Q6413499","itemLabel":"Kingston College","ukprn":"10003674","grid":"grid.468926.7"},{"item":"http://www.wikidata.org/entity/Q6481422","itemLabel":"Lambeth College","ukprn":"10003755","grid":"grid.468959.f"},{"item":"http://www.wikidata.org/entity/Q6841844","itemLabel":"Middlesbrough College","ukprn":"10004344","grid":"grid.469072.e"},{"item":"http://www.wikidata.org/entity/Q7519171","itemLabel":"Simon Langton Grammar School for Boys","ukprn":"10005849","grid":"grid.422361.0"},{"item":"http://www.wikidata.org/entity/Q7600102","itemLabel":"Stanmore College","ukprn":"10009439","grid":"grid.469151.e"},{"item":"http://www.wikidata.org/entity/Q7894499","itemLabel":"University Academy Holbeach","ukprn":"10034999","grid":"grid.449649.2"},{"item":"http://www.wikidata.org/entity/Q8026991","itemLabel":"Wirral Metropolitan College","ukprn":"10007553","grid":"grid.463081.8"},{"item":"http://www.wikidata.org/entity/Q5311834","itemLabel":"Dudley College of Technology","ukprn":"10007924","grid":"grid.462118.8"},{"item":"http://www.wikidata.org/entity/Q1075104","itemLabel":"University of Essex","ukprn":"10007791","grid":"grid.8356.8"},{"item":"http://www.wikidata.org/entity/Q1144673","itemLabel":"Royal Academy of Music","ukprn":"10007835","grid":"grid.421653.7"},{"item":"http://www.wikidata.org/entity/Q499510","itemLabel":"University of Liverpool","ukprn":"10006842","grid":"grid.10025.36"},{"item":"http://www.wikidata.org/entity/Q937482","itemLabel":"Edge Hill University","ukprn":"10007823","grid":"grid.255434.1"},{"item":"http://www.wikidata.org/entity/Q5025507","itemLabel":"Cambridge Regional College","ukprn":"10001116","grid":"grid.468744.d"},{"item":"http://www.wikidata.org/entity/Q5658944","itemLabel":"Harlow College","ukprn":"10002899","grid":"grid.435112.0"},{"item":"http://www.wikidata.org/entity/Q7565336","itemLabel":"South & City College Birmingham","ukprn":"10005967","grid":"grid.469227.c"},{"item":"http://www.wikidata.org/entity/Q172771","itemLabel":"Royal Navy","ukprn":"10033438","grid":"grid.437496.b"},{"item":"http://www.wikidata.org/entity/Q6519168","itemLabel":"Leicester College","ukprn":"10003867","grid":"grid.468986.d"},{"item":"http://www.wikidata.org/entity/Q3577898","itemLabel":"Chetham's School of Music","ukprn":"10008631","grid":"grid.468672.9"},{"item":"http://www.wikidata.org/entity/Q4836273","itemLabel":"BPP University","ukprn":"10031982","grid":"grid.417785.8"},{"item":"http://www.wikidata.org/entity/Q448403","itemLabel":"Buckinghamshire New University","ukprn":"10000975","grid":"grid.411820.e"},{"item":"http://www.wikidata.org/entity/Q5687445","itemLabel":"Haywood Academy","ukprn":"10035046","grid":"grid.502821.c"},{"item":"http://www.wikidata.org/entity/Q6410900","itemLabel":"King's College School","ukprn":"10016322","grid":"grid.464613.2"},{"item":"http://www.wikidata.org/entity/Q7232436","itemLabel":"Portsmouth College","ukprn":"10005158","grid":"grid.502894.2"},{"item":"http://www.wikidata.org/entity/Q7330738","itemLabel":"Richmond, The American International University in London","ukprn":"10005470","grid":"grid.417904.f"},{"item":"http://www.wikidata.org/entity/Q16995868","itemLabel":"Lancaster and Morecambe College","ukprn":"10003768","grid":"grid.468962.7"},{"item":"http://www.wikidata.org/entity/Q1333399","itemLabel":"University of Leicester","ukprn":"10007796","grid":"grid.9918.9"},{"item":"http://www.wikidata.org/entity/Q9357897","itemLabel":"University of Law","ukprn":"10039956","grid":"grid.417909.2"},{"item":"http://www.wikidata.org/entity/Q1296153","itemLabel":"University of the West of Scotland","ukprn":"10007800","grid":"grid.15756.30"},{"item":"http://www.wikidata.org/entity/Q7055590","itemLabel":"North Hertfordshire College","ukprn":"10004690","grid":"grid.469033.b"},{"item":"http://www.wikidata.org/entity/Q7085632","itemLabel":"The Oldham College","ukprn":"10006770","grid":"grid.469193.0"},{"item":"http://www.wikidata.org/entity/Q7383524","itemLabel":"Rutlish School","ukprn":"10017396","grid":"grid.481117.a"},{"item":"http://www.wikidata.org/entity/Q967165","itemLabel":"University of York","ukprn":"10007167","grid":"grid.5685.e"},{"item":"http://www.wikidata.org/entity/Q458393","itemLabel":"Durham University","ukprn":"10007143","grid":"grid.8250.f"},{"item":"http://www.wikidata.org/entity/Q748106","itemLabel":"Glasgow School of Art","ukprn":"10002681","grid":"grid.420422.2"},{"item":"http://www.wikidata.org/entity/Q1072029","itemLabel":"University of Wales","ukprn":"10008574","grid":"grid.8155.9"},{"item":"http://www.wikidata.org/entity/Q4861904","itemLabel":"Barnsley College","ukprn":"10000536","grid":"grid.463772.3"},{"item":"http://www.wikidata.org/entity/Q7989410","itemLabel":"Weston College","ukprn":"10007459","grid":"grid.463065.2"},{"item":"http://www.wikidata.org/entity/Q5261435","itemLabel":"Derby College","ukprn":"10001919","grid":"grid.508532.9"},{"item":"http://www.wikidata.org/entity/Q5956693","itemLabel":"Hymers College","ukprn":"10008283","grid":"grid.502827.a"},{"item":"http://www.wikidata.org/entity/Q2010561","itemLabel":"University of Buckingham","ukprn":"10007787","grid":"grid.90685.32"},{"item":"http://www.wikidata.org/entity/Q3183295","itemLabel":"University of Derby","ukprn":"10007851","grid":"grid.57686.3a"},{"item":"http://www.wikidata.org/entity/Q7590448","itemLabel":"St. Mary's University College","ukprn":"10008026","grid":"grid.417906.d"},{"item":"http://www.wikidata.org/entity/Q56583901","itemLabel":"Cardiff West Community High School","ukprn":"10065688","grid":"grid.498093.f"},{"item":"http://www.wikidata.org/entity/Q4916446","itemLabel":"Birkenhead Sixth Form College","ukprn":"10064686","grid":"grid.468794.0"},{"item":"http://www.wikidata.org/entity/Q7717418","itemLabel":"The Bewdley School","ukprn":"10019145","grid":"grid.501022.4"},{"item":"http://www.wikidata.org/entity/Q1470817","itemLabel":"University of the Highlands and Islands","ukprn":"10007114","grid":"grid.23378.3d"}]